<?xml version="1.0" encoding="utf-8"?>
<!DOCTYPE hibernate-mapping PUBLIC "-//Hibernate/Hibernate Mapping DTD 3.0//EN"
"http://www.hibernate.org/dtd/hibernate-mapping-3.0.dtd">
<!-- 
    Mapping file autogenerated by MyEclipse Persistence Tools
-->
<hibernate-mapping>
    <class name="testentity.Users" table="users" schema="dbo" catalog="WeJob">
        <id name="userid" type="java.lang.String">
            <column name="userid" length="50" />
            <generator class="identity"></generator>
        </id>
        <property name="id" type="java.lang.Integer">
            <column name="id" not-null="true" />
        </property>
        <property name="userpassword" type="java.lang.String">
            <column name="userpassword" length="50" />
        </property>
        <property name="username" type="java.lang.String">
            <column name="username" length="50" />
        </property>
        <property name="useremail" type="java.lang.String">
            <column name="useremail" length="50" />
        </property>
        <property name="userphone" type="java.lang.String">
            <column name="userphone" length="50" />
        </property>
        <property name="useraddress" type="java.lang.String">
            <column name="useraddress" length="50" />
        </property>
        <property name="userimg" type="java.lang.String">
            <column name="userimg" length="50" />
        </property>
        <property name="userstate" type="java.lang.String">
            <column name="userstate" length="50" not-null="true" />
        </property>
        <set name="applies" inverse="true">
            <key>
                <column name="userid" length="50" />
            </key>
            <one-to-many class="testentity.Apply" />
        </set>
    </class>
</hibernate-mapping>
